hicompass/__init__.py
hicompass/cli.py
hicompass/commands/__init__.py
hicompass/commands/predicting.py
hicompass/commands/preprocess_atac.py
hicompass/commands/preprocess_dna.py
hicompass/commands/preprocess_hic_norm.py
hicompass/commands/preprocess_hic_to_npz.py
hicompass/commands/training.py
hicompass/predicting/PredictDataset.py
hicompass/predicting/PredictModel.py
hicompass/predicting/__init__.py
hicompass/predicting/blocks.py
hicompass/predicting/chromosome_dataset_predict.py
hicompass/predicting/data_feature.py
hicompass/predicting/utils.py
hicompass/preprocess/__init__.py
hicompass/preprocess/atac.py
hicompass/preprocess/hic_norm.py
hicompass/preprocess/hic_to_npz.py
hicompass/train/HicompassDataset.py
hicompass/train/HicompassModel.py
hicompass/train/HicompassTrain.py
hicompass/train/__init__.py
hicompass/train/blocks.py
hicompass/train/data_feature.py
hicompass-1.0.2.dist-info/licenses/LICENSE
hicompass-1.0.2.dist-info/METADATA
hicompass-1.0.2.dist-info/WHEEL
hicompass-1.0.2.dist-info/entry_points.txt
hicompass-1.0.2.dist-info/top_level.txt
hicompass-1.0.2.dist-info/RECORD
