Metadata-Version: 2.4
Name: hicompass
Version: 1.0.2
Summary: Hi-Compass: Depth-aware deep learning framework for cell-type-specific chromatin interaction prediction from ATAC-seq
Home-page: https://github.com/EndeavourSyc/Hi-Compass/
Author: Yuanchen Sun
Author-email: 2247143021@qq.com
License: MIT
Classifier: Programming Language :: Python
Classifier: Programming Language :: Python :: 3
Classifier: Programming Language :: Python :: 3.8
Classifier: Programming Language :: Python :: 3.9
Classifier: Programming Language :: Python :: 3.10
Classifier: Programming Language :: Python :: 3.11
Classifier: License :: OSI Approved :: MIT License
Classifier: Operating System :: OS Independent
Classifier: Topic :: Scientific/Engineering :: Bio-Informatics
Requires-Python: >=3.8
License-File: LICENSE
Requires-Dist: numpy
Requires-Dist: pandas
Requires-Dist: scikit-image
Requires-Dist: pyBigWig
Requires-Dist: cooler
Requires-Dist: pysam
Requires-Dist: piq
Requires-Dist: matplotlib
Dynamic: author
Dynamic: author-email
Dynamic: classifier
Dynamic: description
Dynamic: description-content-type
Dynamic: home-page
Dynamic: license
Dynamic: license-file
Dynamic: requires-dist
Dynamic: requires-python
Dynamic: summary
